prime_finder/__init__.py
prime_finder/prime.py
prime_finder_srk-0.1.0.dist-info/LICENSE
prime_finder_srk-0.1.0.dist-info/METADATA
prime_finder_srk-0.1.0.dist-info/WHEEL
prime_finder_srk-0.1.0.dist-info/top_level.txt
prime_finder_srk-0.1.0.dist-info/RECORD
