Metadata-Version: 2.2
Name: prime-finder-srk
Version: 0.1.0
Summary: A Python library for finding the nth prime number
Author-email: Shaharukh Khan <shaharukh.khan@olakrutrim.com>
License: MIT License
Keywords: prime,numbers,mathematics
Classifier: License :: OSI Approved :: MIT License
Classifier: Operating System :: OS Independent
Requires-Python: >=3.8
License-File: LICENSE
Provides-Extra: dev
Requires-Dist: pytest>=7.0; extra == "dev"
Requires-Dist: pytest-cov>=4.0; extra == "dev"
Requires-Dist: black>=22.0; extra == "dev"
Requires-Dist: isort>=5.0; extra == "dev"
Requires-Dist: mypy>=1.0; extra == "dev"
